MANIFEST.in
README.rst
setup.py
vaurienclient/__init__.py
vaurienclient.egg-info/PKG-INFO
vaurienclient.egg-info/SOURCES.txt
vaurienclient.egg-info/dependency_links.txt
vaurienclient.egg-info/entry_points.txt
vaurienclient.egg-info/not-zip-safe
vaurienclient.egg-info/requires.txt
vaurienclient.egg-info/top_level.txt
vaurienclient/ext/__init__.py
vaurienclient/ext/_marteau.py