Metadata-Version: 1.0
Name: vaurienclient
Version: 1.1
Summary: Client for the TCP Chaos Proxy
Home-page: UNKNOWN
Author: Mozilla Foundation & contributors
Author-email: services-dev@lists.mozila.org
License: UNKNOWN
Platform: UNKNOWN
Classifier: Programming Language :: Python
Classifier: License :: OSI Approved :: Apache Software License
Classifier: Development Status :: 1 - Planning
